codesim/__init__.py
codesim/__main__.py
codesim-0.0.0.dist-info/METADATA
codesim-0.0.0.dist-info/WHEEL
codesim-0.0.0.dist-info/entry_points.txt
codesim-0.0.0.dist-info/top_level.txt
codesim-0.0.0.dist-info/RECORD
