Metadata-Version: 2.1
Name: codesim
Version: 0.0.0
Summary: A tool to measure code similarity.
Home-page: https://github.com/StardustDL/codesim
Author: StardustDL
Author-email: stardustdl@163.com
License: UNKNOWN
Project-URL: Source Code, https://github.com/StardustDL/codesim
Project-URL: Changes, https://github.com/StardustDL/codesim/releases
Project-URL: Documentation, https://github.com/StardustDL/codesim
Project-URL: Bug Tracker, https://github.com/StardustDL/codesim/issues
Platform: UNKNOWN
Classifier: License :: OSI Approved :: Mozilla Public License 2.0 (MPL 2.0)
Classifier: Operating System :: OS Independent
Classifier: Programming Language :: Python :: 3
Classifier: Programming Language :: Python :: 3.7
Classifier: Programming Language :: Python :: 3.8
Classifier: Programming Language :: Python :: 3.9
Classifier: Programming Language :: Python :: 3.10
Classifier: Programming Language :: Python :: Implementation :: CPython
Classifier: Topic :: Utilities
Requires-Python: >=3.7
Requires-Dist: click (>=8.0.3)
Requires-Dist: PyYaml (>=6.0)
Requires-Dist: python-dateutil (>=2.8.2)
Requires-Dist: marko (>=1.1.0)
